{
  "details": [
    {
      "firstname": "Sumathy",
      "lastname": "sri",
      "age": "20",
      "email": "si@gmail.com",
      "phonenumber": "9897947865",
      "city": "2",
      "college": "wcc",
      "department": "mca",
      "id": 1
    },
    {
      "firstname": "Sumathy",
      "lastname": "sri",
      "age": "20",
      "email": "si@gmail.com",
      "phonenumber": "9897947865",
      "city": "2",
      "college": "kdj",
      "department": "ogerho",
      "id": 2
    },
    {
      "firstname": "mathew",
      "lastname": "john",
      "age": "25",
      "email": "mjs@yahoo.com",
      "phonenumber": "9865478521",
      "city": "4",
      "college": "mcc",
      "department": "bca",
      "id": 3
    }
  ]
}